odoo/addons/mail_notification_link/README.rst
odoo/addons/mail_notification_link/__init__.py
odoo/addons/mail_notification_link/__manifest__.py
odoo/addons/mail_notification_link/i18n/it.po
odoo/addons/mail_notification_link/i18n/mail_notification_link.pot
odoo/addons/mail_notification_link/readme/CONTRIBUTORS.md
odoo/addons/mail_notification_link/readme/DESCRIPTION.md
odoo/addons/mail_notification_link/readme/USAGE.md
odoo/addons/mail_notification_link/static/description/icon.png
odoo/addons/mail_notification_link/static/description/index.html
odoo/addons/mail_notification_link/static/src/messaging_menu.xml
odoo/addons/mail_notification_link/static/src/notification_item.esm.js
odoo/addons/mail_notification_link/static/src/notification_item.xml
odoo_addon_mail_notification_link-17.0.1.0.0.4.dist-info/METADATA
odoo_addon_mail_notification_link-17.0.1.0.0.4.dist-info/WHEEL
odoo_addon_mail_notification_link-17.0.1.0.0.4.dist-info/top_level.txt
odoo_addon_mail_notification_link-17.0.1.0.0.4.dist-info/RECORD
